eli5_edgio/__init__.py
eli5_edgio/_decision_path.py
eli5_edgio/_feature_importances.py
eli5_edgio/_feature_names.py
eli5_edgio/_feature_weights.py
eli5_edgio/_graphviz.py
eli5_edgio/base.py
eli5_edgio/base_utils.py
eli5_edgio/catboost2.py
eli5_edgio/explain.py
eli5_edgio/ipython.py
eli5_edgio/lightgbm.py
eli5_edgio/lightning.py
eli5_edgio/permutation_importance.py
eli5_edgio/transform.py
eli5_edgio/utils.py
eli5_edgio/xgboost.py
eli5_edgio/formatters/__init__.py
eli5_edgio/formatters/as_dataframe.py
eli5_edgio/formatters/as_dict.py
eli5_edgio/formatters/features.py
eli5_edgio/formatters/fields.py
eli5_edgio/formatters/html.py
eli5_edgio/formatters/image.py
eli5_edgio/formatters/text.py
eli5_edgio/formatters/text_helpers.py
eli5_edgio/formatters/trees.py
eli5_edgio/formatters/utils.py
eli5_edgio/keras/__init__.py
eli5_edgio/keras/explain_prediction.py
eli5_edgio/keras/gradcam.py
eli5_edgio/lime/__init__.py
eli5_edgio/lime/_vectorizer.py
eli5_edgio/lime/lime.py
eli5_edgio/lime/samplers.py
eli5_edgio/lime/textutils.py
eli5_edgio/lime/utils.py
eli5_edgio/sklearn/__init__.py
eli5_edgio/sklearn/_span_analyzers.py
eli5_edgio/sklearn/explain_prediction.py
eli5_edgio/sklearn/explain_weights.py
eli5_edgio/sklearn/permutation_importance.py
eli5_edgio/sklearn/text.py
eli5_edgio/sklearn/transform.py
eli5_edgio/sklearn/treeinspect.py
eli5_edgio/sklearn/unhashing.py
eli5_edgio/sklearn/utils.py
eli5_edgio/sklearn_crfsuite/__init__.py
eli5_edgio/sklearn_crfsuite/explain_weights.py
eli5_edgio/templates/explain.html
eli5_edgio/templates/feature_importances.html
eli5_edgio/templates/styles.html
eli5_edgio/templates/target_header.html
eli5_edgio/templates/transition_features.html
eli5_edgio/templates/weighted_spans.html
eli5_edgio/templates/weights.html
eli5_edgio/templates/weights_table.html
eli5_edgio/templates/weights_table_row.html
eli5_edgio-0.10.5.dist-info/METADATA
eli5_edgio-0.10.5.dist-info/WHEEL
eli5_edgio-0.10.5.dist-info/top_level.txt
eli5_edgio-0.10.5.dist-info/RECORD
